CanSNPer/__init__.py
CanSNPer/__main__.py
CanSNPer/x2fa.py
CanSNPer/modules/DatabaseConnection.py
CanSNPer/modules/ParseXMFA.py
CanSNPer/modules/__init__.py
CanSNPer_1.1.0-1.1.0.dist-info/LICENSE
CanSNPer_1.1.0-1.1.0.dist-info/METADATA
CanSNPer_1.1.0-1.1.0.dist-info/WHEEL
CanSNPer_1.1.0-1.1.0.dist-info/entry_points.txt
CanSNPer_1.1.0-1.1.0.dist-info/top_level.txt
CanSNPer_1.1.0-1.1.0.dist-info/RECORD
