Metadata-Version: 2.1
Name: CanSNPer-1.1.0
Version: 1.1.0
Summary: CanSNPer: A toolkit for SNP-typing using NGS data.
Home-page: https://github.com/FOI-Bioinformatics/cansnper1.1
Author: David Sundell
Author-email: david.sundell@foi.se
License: GPL'
Keywords: Bioinformatics SNP-typing sequence-data
Platform: UNKNOWN
Classifier: Programming Language :: Python :: 3
Classifier: License :: OSI Approved :: GNU General Public License v3 or later (GPLv3+)
Classifier: Operating System :: OS Independent
Requires-Dist: numpy
Requires-Dist: ete3
